Task_4_5/__init__.py
Task_4_5/functions.py
Task_4_5/jsonData.py
Task_4_5/Task_C_pacages/Academic.py
Task_4_5/Task_C_pacages/Plan.py
Task_4_5/Task_C_pacages/Practice.py
Task_4_5/Task_C_pacages/__init__.py
Task_4_5/Task_C_pacages/Base/Discipline.py
Task_4_5/Task_C_pacages/Base/__init__.py
Task_4_5/Task_C_pacages/Base/function.py
Task_4_5_Maihitooy-0.0.1.dist-info/METADATA
Task_4_5_Maihitooy-0.0.1.dist-info/WHEEL
Task_4_5_Maihitooy-0.0.1.dist-info/top_level.txt
Task_4_5_Maihitooy-0.0.1.dist-info/RECORD
