Metadata-Version: 2.1
Name: Task-4-5-Maihitooy
Version: 0.0.1
Summary: A task
Home-page: UNKNOWN
Author: Maihitooy
Author-email: markevich_maria@bk.ru
License: UNKNOWN
Platform: UNKNOWN
Classifier: Programming Language :: Python :: 3.8
Classifier: License :: OSI Approved :: MIT License
Classifier: Operating System :: OS Independent
Requires-Python: >=3.6
Requires-Dist: argon2-cffi (==21.3.0)
Requires-Dist: argon2-cffi-bindings (==21.2.0)
Requires-Dist: asttokens (==2.0.5)
Requires-Dist: attrs (==21.4.0)
Requires-Dist: backcall (==0.2.0)
Requires-Dist: beautifulsoup4 (==4.11.1)
Requires-Dist: bleach (==5.0.0)
Requires-Dist: certifi (==2021.10.8)
Requires-Dist: cffi (==1.15.0)
Requires-Dist: click (==8.1.1)
Requires-Dist: click-plugins (==1.1.1)
Requires-Dist: cligj (==0.7.2)
Requires-Dist: colorama (==0.4.4)
Requires-Dist: cycler (==0.11.0)
Requires-Dist: debugpy (==1.6.0)
Requires-Dist: decorator (==5.1.1)
Requires-Dist: defusedxml (==0.7.1)
Requires-Dist: entrypoints (==0.4)
Requires-Dist: executing (==0.8.3)
Requires-Dist: fastjsonschema (==2.15.3)
Requires-Dist: fonttools (==4.31.2)
Requires-Dist: ipykernel (==6.13.0)
Requires-Dist: ipython (==8.2.0)
Requires-Dist: ipython-genutils (==0.2.0)
Requires-Dist: ipywidgets (==7.7.0)
Requires-Dist: jedi (==0.18.1)
Requires-Dist: Jinja2 (==3.1.1)
Requires-Dist: jsonschema (==4.4.0)
Requires-Dist: jupyter (==1.0.0)
Requires-Dist: jupyter-client (==7.2.2)
Requires-Dist: jupyter-console (==6.4.3)
Requires-Dist: jupyter-core (==4.9.2)
Requires-Dist: jupyterlab-pygments (==0.2.2)
Requires-Dist: jupyterlab-widgets (==1.1.0)
Requires-Dist: kiwisolver (==1.4.1)
Requires-Dist: llvmlite (==0.38.0)
Requires-Dist: MarkupSafe (==2.1.1)
Requires-Dist: matplotlib (==3.5.1)
Requires-Dist: matplotlib-inline (==0.1.3)
Requires-Dist: mistune (==0.8.4)
Requires-Dist: munch (==2.5.0)
Requires-Dist: nbclient (==0.6.0)
Requires-Dist: nbconvert (==6.5.0)
Requires-Dist: nbformat (==5.3.0)
Requires-Dist: nest-asyncio (==1.5.5)
Requires-Dist: notebook (==6.4.10)
Requires-Dist: numba (==0.55.1)
Requires-Dist: numpy (==1.21.5)
Requires-Dist: packaging (==21.3)
Requires-Dist: pandas (==1.4.1)
Requires-Dist: pandocfilters (==1.5.0)
Requires-Dist: parso (==0.8.3)
Requires-Dist: pickleshare (==0.7.5)
Requires-Dist: Pillow (==9.0.1)
Requires-Dist: prometheus-client (==0.14.1)
Requires-Dist: prompt-toolkit (==3.0.29)
Requires-Dist: psutil (==5.9.0)
Requires-Dist: pure-eval (==0.2.2)
Requires-Dist: pycparser (==2.21)
Requires-Dist: Pygments (==2.11.2)
Requires-Dist: pyparsing (==3.0.7)
Requires-Dist: pyproj (==3.3.0)
Requires-Dist: PyQt5 (==5.15.6)
Requires-Dist: PyQt5-Qt5 (==5.15.2)
Requires-Dist: PyQt5-sip (==12.9.1)
Requires-Dist: pyrsistent (==0.18.1)
Requires-Dist: python-dateutil (==2.8.2)
Requires-Dist: pytz (==2022.1)
Requires-Dist: pywin32 (==303)
Requires-Dist: pywinpty (==2.0.5)
Requires-Dist: pyzmq (==22.3.0)
Requires-Dist: qtconsole (==5.3.0)
Requires-Dist: QtPy (==2.0.1)
Requires-Dist: Send2Trash (==1.8.0)
Requires-Dist: Shapely (==1.8.1.post1)
Requires-Dist: six (==1.16.0)
Requires-Dist: soupsieve (==2.3.2.post1)
Requires-Dist: stack-data (==0.2.0)
Requires-Dist: terminado (==0.13.3)
Requires-Dist: tinycss2 (==1.1.1)
Requires-Dist: tornado (==6.1)
Requires-Dist: traitlets (==5.1.1)
Requires-Dist: wcwidth (==0.2.5)
Requires-Dist: webencodings (==0.5.1)
Requires-Dist: widgetsnbextension (==3.6.0)
